strtypes/__init__.py
strtypes-0.0.2.dist-info/LICENSE
strtypes-0.0.2.dist-info/METADATA
strtypes-0.0.2.dist-info/WHEEL
strtypes-0.0.2.dist-info/top_level.txt
strtypes-0.0.2.dist-info/RECORD
