Metadata-Version: 2.1
Name: strtypes
Version: 0.0.2
Summary: Python library for managing string types
Home-page: https://github.com/ibrag8998/strtypes.git
Author: Ibrahim Gadzhimagomedov
Author-email: ibragdzh@gmail.com
License: UNKNOWN
Platform: UNKNOWN
Classifier: Programming Language :: Python :: 3
Classifier: License :: OSI Approved :: MIT License
Classifier: Operating System :: OS Independent
